MANIFEST.in
README.md
README.rst
requirements.txt
setup.cfg
setup.py
scf.egg-info/PKG-INFO
scf.egg-info/SOURCES.txt
scf.egg-info/dependency_links.txt
scf.egg-info/entry_points.txt
scf.egg-info/requires.txt
scf.egg-info/top_level.txt
tcfcli/__init__.py
tcfcli/cmds/__init__.py
tcfcli/cmds/cli/__init__.py
tcfcli/cmds/cli/cli.py
tcfcli/cmds/configure/__init__.py
tcfcli/cmds/configure/cli.py
tcfcli/cmds/configure/add/__init__.py
tcfcli/cmds/configure/add/cli.py
tcfcli/cmds/configure/change/__init__.py
tcfcli/cmds/configure/change/cli.py
tcfcli/cmds/configure/get/__init__.py
tcfcli/cmds/configure/get/cli.py
tcfcli/cmds/configure/set/__init__.py
tcfcli/cmds/configure/set/cli.py
tcfcli/cmds/deploy/__init__.py
tcfcli/cmds/deploy/cli.py
tcfcli/cmds/deploy/new_cli.py
tcfcli/cmds/eventdata/__init__.py
tcfcli/cmds/eventdata/cli.py
tcfcli/cmds/eventdata/get/__init__.py
tcfcli/cmds/eventdata/get/cli.py
tcfcli/cmds/eventdata/list/__init__.py
tcfcli/cmds/eventdata/list/cli.py
tcfcli/cmds/eventdata/update/__init__.py
tcfcli/cmds/eventdata/update/cli.py
tcfcli/cmds/function/__init__.py
tcfcli/cmds/function/cli.py
tcfcli/cmds/function/delete/__init__.py
tcfcli/cmds/function/delete/cli.py
tcfcli/cmds/function/information/__init__.py
tcfcli/cmds/function/information/cli.py
tcfcli/cmds/function/list/__init__.py
tcfcli/cmds/function/list/cli.py
tcfcli/cmds/init/__init__.py
tcfcli/cmds/init/cli.py
tcfcli/cmds/init/templates/tcf-demo-go1/LICENSE
tcfcli/cmds/init/templates/tcf-demo-go1/cookiecutter.json
tcfcli/cmds/init/templates/tcf-demo-go1/{{cookiecutter.project_name}}/.gitignore
tcfcli/cmds/init/templates/tcf-demo-go1/{{cookiecutter.project_name}}/Makefile
tcfcli/cmds/init/templates/tcf-demo-go1/{{cookiecutter.project_name}}/README.md
tcfcli/cmds/init/templates/tcf-demo-go1/{{cookiecutter.project_name}}/index.go
tcfcli/cmds/init/templates/tcf-demo-go1/{{cookiecutter.project_name}}/template.yaml
tcfcli/cmds/init/templates/tcf-demo-nodejs6.10/LICENSE
tcfcli/cmds/init/templates/tcf-demo-nodejs6.10/cookiecutter.json
tcfcli/cmds/init/templates/tcf-demo-nodejs6.10/{{cookiecutter.project_name}}/.gitignore
