Metadata-Version: 1.0
Name: scf
Version: 0.2.5
Summary: This is a local tools for SCF.
Home-page: https://github.com/tencentyun/scfcli.git
Author: Tencent Cloud
Author-email: qcloud_middleware@qq.com
License: Apache License 2.0
Platform: UNKNOWN
